exvllm/__init__.py
exvllm/cli.py
exvllm/ft_kernel.py
exvllm/libft_kernel.so
exvllm/libnuma.so.1
exvllm/register.py
exvllm/vllm/__init__.py
exvllm/vllm/fused_moe_layers.py
exvllm/vllm/model_loader_utils.py
exvllm-0.0.0.3.dist-info/METADATA
exvllm-0.0.0.3.dist-info/WHEEL
exvllm-0.0.0.3.dist-info/entry_points.txt
exvllm-0.0.0.3.dist-info/top_level.txt
exvllm-0.0.0.3.dist-info/RECORD
