Metadata-Version: 2.1
Name: exvllm
Version: 0.0.0.3
Summary: extend for vllm
Home-page: https://github.com/ztxz16/exvllm
Author: huangyuyang
Author-email: ztxz16@foxmail.com
License: UNKNOWN
Platform: UNKNOWN
Requires-Dist: vllm
Provides-Extra: all
Requires-Dist: vllm ; extra == 'all'
